jsp_exp/__init__.py
jsp_exp/job.py
jsp_exp/jsp.py
jsp_exp/operation.py
jsp_exp-0.1.31.dist-info/WHEEL
jsp_exp-0.1.31.dist-info/METADATA
jsp_exp-0.1.31.dist-info/RECORD
