Metadata-Version: 2.1
Name: jsp-exp
Version: 0.1.31
Summary: ジョブショップスケジューリング問題をpythonのクラスで表現
Home-page: https://github.com/tkp0331/jsp-exp
Author: 鈴木貴大
Author-email: merioda.seven.24@gmail.com
Requires-Python: >=3.7.9,<4.0.0
Classifier: Programming Language :: Python :: 3
Classifier: Programming Language :: Python :: 3.10
Classifier: Programming Language :: Python :: 3.8
Classifier: Programming Language :: Python :: 3.9
Project-URL: Repository, https://github.com/tkp0331/jsp-exp
